tests/__init__.py
tests/conftest.py
tests/test_data.py
tests/test_fields.py
tests/test_file.py
us_birth_data/__init__.py
us_birth_data/_utils.py
us_birth_data/fields.py
us_birth_data/files.py
us_birth_data/final.py
us_birth_data/prepare.py
us_birth_data/data/__init__.py
us_birth_data/data/age_of_mother.parquet
us_birth_data/data/birth_facility.parquet
us_birth_data/data/births.parquet
us_birth_data/data/day_of_week.parquet
us_birth_data/data/delivery_method.parquet
us_birth_data/data/hashes.json
us_birth_data/data/month.parquet
us_birth_data/data/parity.parquet
us_birth_data/data/sex_of_child.parquet
us_birth_data/data/state.parquet
us_birth_data/data/year.parquet
us_birth_data-0.1.4.dist-info/LICENSE
us_birth_data-0.1.4.dist-info/METADATA
us_birth_data-0.1.4.dist-info/WHEEL
us_birth_data-0.1.4.dist-info/top_level.txt
us_birth_data-0.1.4.dist-info/RECORD
