Metadata-Version: 2.1
Name: us-birth-data
Version: 0.1.4
Summary: A pre-processed longitudinal aggregate table of NVSS birth data in the US from 1968 onward
Home-page: https://github.com/Mikuana/us_birth_data
Author: Christopher Boyd
License: UNKNOWN
Platform: UNKNOWN
Classifier: Programming Language :: Python :: 3
Classifier: License :: OSI Approved :: MIT License
Classifier: Operating System :: OS Independent
Requires-Python: >=3.8
Requires-Dist: pandas (>=1.1)
Requires-Dist: pyarrow
Requires-Dist: requests
Requires-Dist: semver
Requires-Dist: tqdm
Provides-Extra: testing
Requires-Dist: pytest ; extra == 'testing'
Requires-Dist: pytest-mock ; extra == 'testing'
Requires-Dist: pytest-cov ; extra == 'testing'
Requires-Dist: rumydata (>=0.5.2) ; extra == 'testing'
